<?xml version="1.0" encoding="utf-8"?>
<message_catalog package_key="dotlrn-fs" locale="ru_RU" charset="utf-8">

  <msg key="All">Все</msg>
  <msg key="All_items">Все элементы(??)</msg>
  <msg key="applet_pretty_name">Хранилище Файлов</msg>
  <msg key="Assignments">Задания</msg>
  <msg key="day">день</msg>
  <msg key="days">дней</msg>
  <msg key="Exams">Экзамены</msg>
  <msg key="Folder">Папка</msg>
  <msg key="Handouts">Материалы для выдачи</msg>
  <msg key="Last_Modified">Дата изм.</msg>
  <msg key="Lecture_Notes">Конспекты Лекций</msg>
  <msg key="lt_community_names_Files">Документы %community_name%</msg>
  <msg key="lt_community_names_Publi">Документы %community_name%, доступные всем</msg>
  <msg key="lt_new_values_Shared_Fil">Документы %new_value%, доступные другим пользователям</msg>
  <msg key="lt_No_top_offending_fold">Папки-нарушители  отсутствуют</msg>
  <msg key="lt_Showing_files_modifie">Документы, измененные за последние %n_past_days% %days_singular_or_plural%</msg>
  <msg key="lt_user_names_Shared_Fil">Документы %user_name%, доступные другим пользователям</msg>
  <msg key="Name">Название</msg>
  <msg key="new_values_Files">Документы %new_value%</msg>
  <msg key="No_contents_found">Содержание не найдено.</msg>
  <msg key="Order_By">Сортировка по</msg>
  <msg key="Projects">Проекты</msg>
  <msg key="Size">Размер</msg>
  <msg key="Size_bytes">Размер (байт)</msg>
  <msg key="Top_Offenders">Главные Нарушители</msg>
  <msg key="Type">Тип</msg>
  <msg key="user_folder_pretty_name">Пользовательская Папка</msg>
  <msg key="User_Folders">Папка Пользователя</msg>
  <msg key="user_names_Files">Документы %user_name%</msg>
</message_catalog>
